epcpy/__init__.py
epcpy/epc_schemes/__init__.py
epcpy/epc_schemes/adi.py
epcpy/epc_schemes/base_scheme.py
epcpy/epc_schemes/bic.py
epcpy/epc_schemes/cpi.py
epcpy/epc_schemes/gdti.py
epcpy/epc_schemes/giai.py
epcpy/epc_schemes/gid.py
epcpy/epc_schemes/ginc.py
epcpy/epc_schemes/grai.py
epcpy/epc_schemes/gsin.py
epcpy/epc_schemes/gsrn.py
epcpy/epc_schemes/gsrnp.py
epcpy/epc_schemes/imovn.py
epcpy/epc_schemes/itip.py
epcpy/epc_schemes/lgtin.py
epcpy/epc_schemes/pgln.py
epcpy/epc_schemes/sgcn.py
epcpy/epc_schemes/sgln.py
epcpy/epc_schemes/sgtin.py
epcpy/epc_schemes/sscc.py
epcpy/epc_schemes/upui.py
epcpy/epc_schemes/usdod.py
epcpy/py.typed
epcpy/utils/__init__.py
epcpy/utils/common.py
epcpy/utils/parsers.py
epcpy/utils/regex.py
epcpy-0.1.8.dist-info/LICENSE
epcpy-0.1.8.dist-info/METADATA
epcpy-0.1.8.dist-info/WHEEL
epcpy-0.1.8.dist-info/entry_points.txt
epcpy-0.1.8.dist-info/RECORD
