Metadata-Version: 2.3
Name: epcpy
Version: 0.1.8
Summary: A Python module for creation, validation, and transformation of EPC representations as defined in GS1's EPC Tag Data Standard.
License: MIT
Keywords: gs1,epc,python,gtin,sgtin
Author: Nedap Retail
Author-email: sander.meinderts@nedap.com
Requires-Python: >=3.8,<4.0
Classifier: Development Status :: 4 - Beta
Classifier: Intended Audience :: Developers
Classifier: License :: OSI Approved :: MIT License
Classifier: Operating System :: OS Independent
Classifier: Programming Language :: Python :: 3
Classifier: Programming Language :: Python :: 3.8
Classifier: Programming Language :: Python :: 3.9
Classifier: Programming Language :: Python :: 3.10
Classifier: Programming Language :: Python :: 3.11
Classifier: Programming Language :: Python :: 3.12
Classifier: Programming Language :: Python :: 3.13
Project-URL: Homepage, https://github.com/nedap/retail-epcpy
Project-URL: Repository, https://github.com/nedap/retail-epcpy
